strtotime.cpython-37m-x86_64-linux-gnu.so
strtotime-1.0.6.dist-info/METADATA
strtotime-1.0.6.dist-info/top_level.txt
strtotime-1.0.6.dist-info/WHEEL
strtotime-1.0.6.dist-info/RECORD
