Metadata-Version: 2.1
Name: strtotime
Version: 1.0.6
Summary: wrapper for timelib
Home-page: https://github.com/ideler/python-strtotime/
Author: Ideler IT-Service GmbH
Author-email: hosting@ideler.de
License: zlib/php
Platform: UNKNOWN
